pyimg/__init__.py
pyimg/setup.py
pyimg/combine/__init__.py
pyimg/combine/_blend.py
pyimg/combine/_overlay.py
pyimg/combine/_stack.py
pyimg/combine/setup.py
pyimg/convert/__init__.py
pyimg/convert/_convert.py
pyimg/convert/setup.py
pyimg/image/__init__.py
pyimg/image/_img.py
pyimg/image/setup.py
pyimg/metric/__init__.py
pyimg/metric/_batch.py
pyimg/metric/_kappa.py
pyimg/metric/setup.py
pyimg/refine/__init__.py
pyimg/refine/_crop.py
pyimg/refine/_pad.py
pyimg/refine/_remove.py
pyimg/refine/setup.py
pyimg-0.1.0.dist-info/AUTHORS.md
pyimg-0.1.0.dist-info/LICENSE
pyimg-0.1.0.dist-info/METADATA
pyimg-0.1.0.dist-info/WHEEL
pyimg-0.1.0.dist-info/top_level.txt
pyimg-0.1.0.dist-info/RECORD
