Metadata-Version: 2.1
Name: pyimg
Version: 0.1.0
Summary: Image analysis utilities in Python
Home-page: https://github.com/PingjunChen/pyimg
Author: Pingjun Chen
Author-email: chenpingjun@gmx.com
License: MIT
Platform: UNKNOWN
Classifier: Development Status :: 1 - Planning
Classifier: Intended Audience :: Developers
Classifier: Intended Audience :: Science/Research
Classifier: License :: OSI Approved :: MIT License
Classifier: Programming Language :: Python
Classifier: Programming Language :: Python :: 3
Classifier: Programming Language :: Python :: 3.6
Classifier: Topic :: Scientific/Engineering
Requires-Dist: numpy (>=1.15.4)
Requires-Dist: Pillow (>=5.3.0)
Requires-Dist: scikit-image (>=0.14.1)
Requires-Dist: opencv-python (>=3.4.4.19)
